odoo/addons/account_avatax_oca/README.rst
odoo/addons/account_avatax_oca/__init__.py
odoo/addons/account_avatax_oca/__manifest__.py
odoo/addons/account_avatax_oca/hooks.py
odoo/addons/account_avatax_oca/data/avalara_salestax_data.xml
odoo/addons/account_avatax_oca/data/avalara_salestax_exemptions.xml
odoo/addons/account_avatax_oca/i18n/account_avatax.pot
odoo/addons/account_avatax_oca/i18n/account_avatax_oca.pot
odoo/addons/account_avatax_oca/models/__init__.py
odoo/addons/account_avatax_oca/models/account_fiscal_position.py
odoo/addons/account_avatax_oca/models/account_move.py
odoo/addons/account_avatax_oca/models/account_tax.py
odoo/addons/account_avatax_oca/models/avalara_salestax.py
odoo/addons/account_avatax_oca/models/avatax_rest_api.py
odoo/addons/account_avatax_oca/models/partner.py
odoo/addons/account_avatax_oca/models/product.py
odoo/addons/account_avatax_oca/models/res_company.py
odoo/addons/account_avatax_oca/readme/CONFIGURE.rst
odoo/addons/account_avatax_oca/readme/CONTRIBUTORS.rst
odoo/addons/account_avatax_oca/readme/CREDITS.rst
odoo/addons/account_avatax_oca/readme/DESCRIPTION.rst
odoo/addons/account_avatax_oca/readme/INSTALL.rst
odoo/addons/account_avatax_oca/readme/ROADMAP.rst
odoo/addons/account_avatax_oca/readme/USAGE.rst
odoo/addons/account_avatax_oca/security/avalara_salestax_security.xml
odoo/addons/account_avatax_oca/security/ir.model.access.csv
odoo/addons/account_avatax_oca/static/description/ATC1.png
odoo/addons/account_avatax_oca/static/description/ATC10.png
odoo/addons/account_avatax_oca/static/description/ATC11.png
odoo/addons/account_avatax_oca/static/description/ATC12.png
odoo/addons/account_avatax_oca/static/description/ATC13.png
odoo/addons/account_avatax_oca/static/description/ATC14.png
odoo/addons/account_avatax_oca/static/description/ATC15.png
odoo/addons/account_avatax_oca/static/description/ATC16.png
odoo/addons/account_avatax_oca/static/description/ATC17.png
odoo/addons/account_avatax_oca/static/description/ATC18.png
odoo14_addon_account_avatax_oca-14.0.4.0.4.dist-info/METADATA
odoo14_addon_account_avatax_oca-14.0.4.0.4.dist-info/WHEEL
odoo14_addon_account_avatax_oca-14.0.4.0.4.dist-info/top_level.txt
odoo14_addon_account_avatax_oca-14.0.4.0.4.dist-info/RECORD
